Metadata-Version: 2.1
Name: lcdb
Version: 0.1.0
Summary: The official Learning Curve Database package
Home-page: https://github.com/fmohr/lcdb
Author: Felix Mohr
Author-email: mail@felixmohr.de
License: MIT
Keywords: learning curves,database,prediction vectors,runtimes,sklearn
Platform: UNKNOWN
Classifier: Development Status :: 3 - Alpha
Classifier: Intended Audience :: Developers
Classifier: Topic :: Software Development :: Build Tools
Classifier: License :: OSI Approved :: MIT License
Classifier: Programming Language :: Python :: 3.7
Classifier: Programming Language :: Python :: 3.8
Classifier: Programming Language :: Python :: 3.9
License-File: LICENSE.txt
